[
  {
    "id": "xxxx",
    "department": "销售部门",
    "category": "职责问题",
    "question": "技术部的人员职责",
    "question_variants": [
      "技术部人员的具体职责是什么？",
      "技术部门负责哪些工作内容？",
      "技术部的工作职责包括哪些方面？",
      "技术部门人员主要负责什么工作？",
      "技术部的岗位职责有哪些？"
    ],
    "answer": "技术部人员主要负责以下职责：\n\n1. 系统开发与维护：负责公司各业务系统的设计、开发、测试和维护工作，确保系统稳定运行。\n\n2. 技术支持：解决用户在使用系统过程中遇到的技术问题，包括登录异常、卡券使用问题等。\n\n3. 数据安全：实施数据加密、备份及恢复措施，防止数据泄露和丢失。\n\n4. 系统优化：根据业务需求不断优化系统性能，提升用户体验。\n\n5. 技术创新：研究新技术并应用到现有系统中，保持技术竞争力。\n\n6. API对接：负责与第三方平台(如支付、地图服务等)的接口开发和维护。\n\n7. 技术文档：编写和维护技术文档，为其他部门提供系统使用指南。\n\n如有系统相关问题，可联系技术部产品经理凤明（电话：13800138000）。"
  },
    {
      "id": "login-error-01",
      "department": "销售部门",
      "category": "登录问题",
      "question": "用户登录提示：系统发生了异常",
      "question_variants": [
        "登录时提示系统异常怎么解决？",
        "为什么我无法登录系统？",
        "登录不了显示系统异常是什么原因？",
        "系统报错无法登录怎么办？"
      ],
      "answer": "系统异常通常有两种原因：\n\n1. 虚拟号段登录限制：系统对以下虚拟号段实施登录限制：167、1700-1709、171、178、191、147。若您使用这些号段，将无法正常登录。\n\n2. 账号风险评分超限：系统会根据用户行为动态评分，若评分≥7分，将触发账号封禁。评分规则包括：\n   - 下单行为：2天内连续下单2场非广东省影院电影（7分）\n   - 下单频率：2天内成功下单超过3场电影（7分）\n   - 卡券绑定：用户绑定卡券数≥5（2分）\n   - 使用范围：卡券涉及单位≥2（2分）\n   - 多设备登录：单个微信号关联登录手机号>2个（7分）\n   - 同IP登录：同一IP下登录手机号≥3个（1分）\n\n解决方案：\n- 虚拟号段用户：请更换为非限制号段手机号登录\n- 评分超限用户：避免高频操作，若需解封请联系客服"
    },
    {
      "id": "card-binding-error-01",
      "department": "销售部门",
      "category": "卡券问题",
      "question": "用户绑卡提示：卡券系统繁忙",
      "question_variants": [
        "绑定卡券时提示系统繁忙是什么原因？",
        "为什么我无法绑定更多卡券？",
        "卡券系统繁忙是什么意思？",
        "尝试绑卡时系统提示繁忙怎么解决？"
      ],
      "answer": "当系统提示\"卡券系统繁忙\"，通常有以下两种原因：\n\n1. 绑卡数量已达上限：每个销售单有最大绑卡数量限制（例如7张）。若尝试绑定超出限制的卡券，系统会提示\"卡券系统繁忙\"。\n\n2. 公司维度限制：若已绑定第一家公司的卡券，在绑定第二家公司的卡券时，仅允许绑定1张，超出此限制会触发相同提示。\n\n解决方案：如需提高绑卡数量上限，请联系运营部申请调整配置。"
    },
    {
      "id": "banner-size-01",
      "department": "运营部门",
      "category": "UI设计",
      "question": "商城首页banner尺寸？",
      "question_variants": [
        "商城首页的banner图片应该设置多大？",
        "首页banner的尺寸规格是多少？",
        "商城banner图尺寸要求是什么？",
        "主页banner的像素大小是多少？"
      ],
      "answer": "商城首页banner的标准尺寸为351x160像素（宽x高）。请确保按此尺寸制作图片，以获得最佳显示效果。"
    },
    {
      "id": "movie-fail-01",
      "department": "客服部",
      "category": "订单问题",
      "question": "电影订单一直出票失败。",
      "question_variants": [
        "为什么我的电影订单无法出票？",
        "电影票购买后一直提示失败",
        "出票失败是什么原因？",
        "为什么我买的电影票一直不出票？"
      ],
      "answer": "电影订单出票失败的原因是系统账户余额不足。这意味着我们用于支付电影票的账户暂时没有足够资金完成交易。技术团队将尽快充值账户解决此问题。如有紧急需求，请联系客服处理。"
    },
    {
        "id": "birthday-banner-01",
        "department": "运营部门",
        "category": "UI设计",
        "question": "生日慧banner尺寸？",
        "question_variants": [
          "生日慧活动的banner尺寸是多少？",
          "生日慧页面banner要用什么规格？",
          "生日慧的banner像素要求是什么？",
          "生日慧专区的banner大小是多少？"
        ],
        "answer": "生日慧banner的标准尺寸为375x400像素（宽x高）。请按此尺寸规格设计生日慧页面的banner图片，以确保最佳显示效果。"
      },
      {
        "id": "card-usage-01",
        "department": "客服部",
        "category": "卡券问题",
        "question": "三张50的次卡为什么不能买两张69.9的票？",
        "question_variants": [
          "为什么三张50元次卡无法购买两张69.9元的票？",
          "我有三张50元次卡，为什么买不了两张69.9的票？",
          "次卡不够买两张69.9票的原因是什么？",
          "三张50元卡不能支付两张69.9元票是什么问题？"
        ],
        "answer": "这是因为次卡的使用规则限制。两张69.9元票总价为139.8元，使用两张50元次卡后，剩余需要补差39.8元（每张票19.9元）。但第三张50元次卡只能补一张票的差价19.9元，不能同时补两张票的差价。系统设计上，每张次卡只能对应一张票的补差，不能拆分使用。"
      },
      {
        "id": "two-seats-usage-01",
        "department": "客服部",
        "category": "卡券问题",
        "question": "开通了两票三座，用户使用过一次两票三座后面用不了了？",
        "question_variants": [
          "为什么两票三座使用一次后就无法再使用？",
          "两票三座卡为什么只能用一次？",
          "使用过两票三座后无法再次使用是什么原因？",
          "两票三座权益为什么只能使用一次？"
        ],
        "answer": "两票三座功能在系统中设计为一个销售单的卡只能使用一次。这意味着一旦您使用了该权益购票，即使没有用完所有座位数，该权益也会被标记为已使用，无法再次使用。这是系统的功能限制，不是卡券失效或系统故障。"
      },
      {
        "id": "account-binding-01",
        "department": "运营部",
        "category": "账号问题",
        "question": "用户登录时显示：此账号在平台已绑定另一微信，请使用该微信登录",
        "question_variants": [
          "登录提示账号已绑定其他微信怎么解决？",
          "如何解除微信账号绑定？",
          "账号被绑定到其他微信怎么办？",
          "提示账号已被其他微信绑定如何处理？"
        ],
        "answer": "解决方法：需要管理员操作解绑。首先获取用户的微信昵称，然后在后台会员管理功能中，找到该用户，点击\"操作-更多\"，执行解绑操作。解绑后，用户可以使用当前微信重新绑定并登录系统。如果用户无法提供之前绑定的微信信息，请联系系统管理员协助处理。"
      },
      {
        "id": "card-payment-fail-01",
        "department": "客服部",
        "category": "卡券问题",
        "question": "用户选择商品下单，无法使用卡券支付",
        "question_variants": [
          "为什么我选了商品但用不了卡券支付？",
          "卡券无法在下单时使用是什么原因？",
          "商品无法使用卡券结算怎么办？",
          "下单时卡券不可用是什么问题？"
        ],
        "answer": "用户无法使用卡券支付通常有两种原因：\n\n1. 卡券没有配置该商品的品牌购买权限：每张卡券都有特定的适用品牌范围，如果当前商品品牌不在您的卡券使用范围内，将无法使用该卡券支付。\n\n2. 卡券只配置了显示栏目，没有配置购买栏目：系统中卡券有两种权限设置，\"显示\"和\"购买\"。如果卡券只有显示权限而没有购买权限，您可以看到相关商品但无法使用卡券购买。\n\n解决方案：请联系客服确认您的卡券使用范围，或选择卡券适用范围内的其他商品。"
      },
      {
        "id": "missing-card-01",
        "department": "客服部",
        "category": "卡券问题",
        "question": "用户反馈登录后看不到卡券",
        "question_variants": [
          "为什么我登录后看不到我的卡券？",
          "卡券在哪里查看？登录后找不到",
          "我的卡券不见了怎么办？",
          "登录系统后无法查看卡券"
        ],
        "answer": "您看不到卡券可能是因为您使用的是专区卡，并且绑定了商城0元卡，系统默认进入了主商城。解决方法：请在\"我的页面\"中，找到并点击\"切换商城\"按钮，选择切换到对应的专区商城。不同专区的卡券只能在对应专区内查看和使用，这是系统设计的功能分离机制。"
      },
      {
        "id": "flash-sale-01",
        "department": "运营部",
        "category": "商城问题",
        "question": "进入秒杀专区页面，除了秒杀商品，下面还会出现 推荐商品 这种嘛",
        "question_variants": [
          "秒杀专区会显示非秒杀的推荐商品吗？",
          "秒杀页面是否有其他推荐商品？",
          "秒杀专区只展示秒杀商品吗？",
          "秒杀活动页面会有普通商品推荐吗？"
        ],
        "answer": "秒杀专区页面只会展示秒杀商品，不会出现\"推荐商品\"等其他类型的商品。这是为了保持秒杀专区的专注性和用户体验，确保用户能快速找到和购买秒杀商品。如果您在秒杀专区看到了非秒杀商品，可能是系统配置异常，请联系运营部门处理。"
      },
      
      {
        "id": "coupon-expiration-01",
        "department": "运营部",
        "category": "优惠券问题",
        "question": "C端优惠券的兑换码是什么时候兑换都可以的嘛，有没有兑换期限",
        "question_variants": [
          "优惠券兑换码有没有使用期限？",
          "C端优惠券兑换码什么时候失效？",
          "优惠券的兑换码有时间限制吗？",
          "兑换码可以一直使用吗？"
        ],
        "answer": "目前系统中的C端优惠券兑换码没有设置时间限制，用户可以在任何时候进行兑换。不过需要注意的是，虽然兑换码本身没有期限限制，但兑换后得到的优惠券可能会有使用期限，请在兑换后查看优惠券详情中的有效期信息。"
      },
      
      
      {
        "id": "api-limit-01",
        "department": "运营部",
        "category": "系统问题",
        "question": "导入门店，这个地址我在百度地图上搜得到，为什么会报错：地址信息不正确，请重新输入",
        "question_variants": [
          "为什么地址信息正确但系统提示不正确？",
          "导入门店时地址验证失败怎么解决？",
          "系统提示地址信息不正确是什么原因？",
          "百度地图能搜到的地址为什么导入失败？"
        ],
        "answer": "系统报错\"地址信息不正确\"并非因为地址本身有误，而是因为今日百度API账户的使用额度已用完。系统需要调用百度地图API进行地址验证，当API调用次数超过每日限额时，即使地址正确也会验证失败。解决方法：请等待次日额度重置后再尝试导入，或联系技术部门增加API调用额度。"
      },

      {
        "id": "api-limit-02",
        "department": "运营部",
        "category": "系统问题",
        "question": "混合支付是什么",
        "question_variants": [],
        "answer": "混合支付，目前可选择卡券+钱包+微信一起付款。\n 1.如选择卡券+钱包+微信付款，因为微信付款成功不是立刻通知，所以会先将卡券与钱包先付款，等微信通知成功后再将订单改成已支付\n2.如微信支付失败，则立刻触发卡券和钱包退款。\n3.如是用户未微信支付，则可以在订单列表待支付中重新支付。或手动取消订单和等待订单自动取消，触发钱包和卡券退款"
      }
  ]